{
    "fluentMethods": true,
    "relationships": [
        {
            "relationshipType": "many-to-one",
            "relationshipName": "visit",
            "otherEntityName": "visit",
            "otherEntityField": "id"
        }
    ],
    "fields": [
        {
            "fieldName": "work",
            "fieldType": "String",
            "fieldValidateRules": [
                "required"
            ]
        },
        {
            "fieldName": "quantity",
            "fieldType": "Long",
            "fieldValidateRules": [
                "required"
            ]
        },
        {
            "fieldName": "priceOne",
            "fieldType": "BigDecimal",
            "fieldValidateRules": [
                "required"
            ]
        },
        {
            "fieldName": "cost",
            "fieldType": "BigDecimal",
            "fieldValidateRules": [
                "required"
            ]
        }
    ],
    "changelogDate": "20170416203638",
    "entityTableName": "work",
    "dto": "no",
    "pagination": "no",
    "service": "no"
}